nexius/__init__.py
nexius/core.py
nexius/log.py
nexius-0.1.0.dist-info/LICENSE
nexius-0.1.0.dist-info/METADATA
nexius-0.1.0.dist-info/WHEEL
nexius-0.1.0.dist-info/top_level.txt
nexius-0.1.0.dist-info/RECORD
