Metadata-Version: 2.1
Name: nexius
Version: 0.1.0
Summary: A Python library with multiple utilities
Home-page: https://github.com/roc4et/nexius
Author: roc4et
Author-email: x@roc4et.de
Keywords: logging utility colorful-output
Classifier: Development Status :: 3 - Alpha
Classifier: Intended Audience :: Developers
Classifier: License :: OSI Approved :: MIT License
Classifier: Programming Language :: Python :: 3
Classifier: Programming Language :: Python :: 3.7
Classifier: Programming Language :: Python :: 3.8
Classifier: Programming Language :: Python :: 3.9
Classifier: Programming Language :: Python :: 3.10
Requires-Python: >=3.7
License-File: LICENSE
Requires-Dist: colorama>=0.4.4
